README.txt
setup.py
collective/__init__.py
collective.js.innerfade.egg-info/PKG-INFO
collective.js.innerfade.egg-info/SOURCES.txt
collective.js.innerfade.egg-info/dependency_links.txt
collective.js.innerfade.egg-info/entry_points.txt
collective.js.innerfade.egg-info/namespace_packages.txt
collective.js.innerfade.egg-info/not-zip-safe
collective.js.innerfade.egg-info/requires.txt
collective.js.innerfade.egg-info/top_level.txt
collective/js/__init__.py
collective/js/innerfade/__init__.py
collective/js/innerfade/configure.zcml
collective/js/innerfade/interfaces.py
collective/js/innerfade/tests.py
collective/js/innerfade/browser/__init__.py
collective/js/innerfade/browser/configure.zcml
collective/js/innerfade/browser/folder_innerfade_macro.pt
collective/js/innerfade/browser/folder_innerfade_view.pt
collective/js/innerfade/browser/folder_innerfade_view.py
collective/js/innerfade/browser/images/arrow_8x69.gif
collective/js/innerfade/browser/images/arrow_8x69.png
collective/js/innerfade/browser/images/button_back_2x20.png
collective/js/innerfade/browser/javascripts/README.mdown
collective/js/innerfade/browser/javascripts/collective.innerfade.js
collective/js/innerfade/browser/javascripts/jquery.innerfade.js
collective/js/innerfade/browser/javascripts/jquery.innerfade.min.js
collective/js/innerfade/browser/stylesheets/collective.innerfade.css
collective/js/innerfade/profiles/default/browserlayer.xml
collective/js/innerfade/profiles/default/cssregistry.xml
collective/js/innerfade/profiles/default/jsregistry.xml
collective/js/innerfade/profiles/default/types/Folder.xml
docs/HISTORY.txt
docs/INSTALL.txt
docs/LICENSE.GPL
docs/LICENSE.txt