Metadata-Version: 1.0
Name: collective.js.innerfade
Version: 1.0
Summary: jQuery Innerfade plugin and additional view for ATFolder
Home-page: http://svn.plone.org/svn/collective/collective.js.innerfade
Author: Goldmund, Wyldebeast & Wunderliebe
Author-email: info@gw20e.com
License: GPL
Platform: UNKNOWN
Classifier: Framework :: Plone
Classifier: Programming Language :: Python
